hello_world_mcp_server2026_happy/__init__.py
hello_world_mcp_server2026_happy-0.1.0.dist-info/WHEEL
hello_world_mcp_server2026_happy-0.1.0.dist-info/entry_points.txt
hello_world_mcp_server2026_happy-0.1.0.dist-info/METADATA
hello_world_mcp_server2026_happy-0.1.0.dist-info/RECORD
