Metadata-Version: 2.3
Name: hello-world-mcp-server2026-happy
Version: 0.1.0
Summary: Add your description here
Requires-Dist: mcp[cli]
Requires-Python: >=3.13
